{
  "adjectives": [
    "almond",
    "aromatic",
    "cherry",
    "chocolate",
    "citrus",
    "cream",
    "edible",
    "erect",
    "flowering",
    "fragrant",
    "ginger",
    "hardy",
    "herbaceous",
    "herbal",
    "honey",
    "medicinal",
    "mint",
    "olive",
    "ornamental",
    "peanut",
    "perennial",
    "rhizomatous",
    "salt",
    "savory",
    "succulent",
    "vegetable",
    "woody"
  ],
  "imagenet": "herb",
  "monster_type": "herb",
  "nouns": [
    "bolivian",
    "verbena",
    "woodruff",
    "culantro",
    "mitsuba",
    "savory",
    "epazote",
    "houttuynia",
    "boldo",
    "vietnamese",
    "gioi",
    "perilla",
    "santa",
    "lovage",
    "balm",
    "chives",
    "coriander",
    "hoja",
    "garlic",
    "hemp",
    "kinh",
    "oregano",
    "sansho",
    "tarragon",
    "cilantro",
    "lemon",
    "hyssop",
    "jimbu",
    "cicely",
    "sorrel",
    "leaf",
    "sage",
    "indian",
    "thai",
    "cordata",
    "limnophila",
    "shiso",
    "mugwort",
    "parsley",
    "holy",
    "myrtle",
    "lavender",
    "marjoram",
    "rosemary",
    "cress",
    "dill",
    "chervil",
    "angelica",
    "aromatica",
    "thyme",
    "basil",
    "borage",
    "grass",
    "mint",
    "curry"
  ],
  "verbs": [
    "bean",
    "berry",
    "bloom",
    "butter",
    "cake",
    "cream",
    "erect",
    "flavor",
    "frost",
    "fruit",
    "garden",
    "ginger",
    "grass",
    "honey",
    "leaf",
    "mushroom",
    "pepper",
    "plant",
    "rice",
    "salt",
    "stew"
  ],
  "wikipedia": "herb"
}