{
  "adjectives": [
    "amphibian",
    "amphipod",
    "animal",
    "ant",
    "aquatic",
    "arboreal",
    "avian",
    "bacterial",
    "beetle",
    "benthic",
    "bitten",
    "brachiopod",
    "breeding",
    "brood",
    "bugs",
    "canine",
    "carnivorous",
    "cichlid",
    "colubrid",
    "commensal",
    "copepod",
    "crocodilian",
    "crustacean",
    "cyprinid",
    "deep-sea",
    "endemic",
    "extinct",
    "feline",
    "feral",
    "flowering",
    "fossorial",
    "free-living",
    "fungal",
    "genetic",
    "hominid",
    "humanoid",
    "infect",
    "invasive",
    "invertebrate",
    "leguminous",
    "mammalian",
    "marsupial",
    "microbial",
    "microscopic",
    "monotypic",
    "mutant",
    "nocturnal",
    "nymphalid",
    "parasitic",
    "pathogenic",
    "pet",
    "primate",
    "rabid",
    "reptile",
    "reptilian",
    "semiaquatic",
    "skulking",
    "spiny",
    "theropod",
    "ungulate",
    "vampiric",
    "venomous",
    "vertebrate"
  ],
  "imagenet": "rodent",
  "monster_type": "rodent",
  "nouns": [
    "gnawer",
    "chinchilla",
    "porcupine",
    "hedgehog",
    "jerboa",
    "aperea",
    "viscacha",
    "chinchillon",
    "mara",
    "mouse",
    "fieldmouse",
    "muskrat",
    "musquash",
    "paca",
    "coypu",
    "hamster",
    "agouti",
    "squirrel",
    "hackee",
    "gopher",
    "spermophile",
    "suslik",
    "souslik",
    "flickertail",
    "baronduki",
    "baranduki",
    "barunduki",
    "burunduki",
    "chipmunk",
    "chickeree",
    "taguan",
    "capybara",
    "capibara",
    "gopher",
    "murine",
    "abrocome",
    "marmot",
    "rockchuck",
    "groundhog",
    "woodchuck",
    "whistler",
    "beaver",
    "dormouse",
    "lerot",
    "loir",
    "sewellel",
    "gerbil",
    "gerbille",
    "jird",
    "packrat",
    "vole",
    "phenacomys"
  ],
  "verbs": [
    "bird",
    "bite",
    "bitten",
    "infect",
    "prey",
    "shark",
    "tick",
    "worm"
  ],
  "wikipedia": "rodent"
}